ahmadsMathLibrary/IterSolver.py
ahmadsMathLibrary/__init__.py
ahmadsMathLibrary/decompositions.py
ahmadsMathLibrary/eigenthings.py
ahmadsMathLibrary/linear_algebra.py
ahmadsMathLibrary-0.1.3.dist-info/METADATA
ahmadsMathLibrary-0.1.3.dist-info/WHEEL
ahmadsMathLibrary-0.1.3.dist-info/top_level.txt
ahmadsMathLibrary-0.1.3.dist-info/RECORD
