Metadata-Version: 2.1
Name: ahmadsMathLibrary
Version: 0.1.3
Requires-Dist: numpy >=1.21.0
